pygments_sql_pl_lexer-0.3.dist-info/DESCRIPTION.rst
pygments_sql_pl_lexer-0.3.dist-info/METADATA
pygments_sql_pl_lexer-0.3.dist-info/RECORD
pygments_sql_pl_lexer-0.3.dist-info/WHEEL
pygments_sql_pl_lexer-0.3.dist-info/entry_points.txt
pygments_sql_pl_lexer-0.3.dist-info/metadata.json
pygments_sql_pl_lexer-0.3.dist-info/top_level.txt
sql_pl_lexer/__init__.py
