Metadata-Version: 2.0
Name: pygments-sql-pl-lexer
Version: 0.3
Summary: Pygments lexer for SQL PL (SQL Procedural Language), the DB2 implementation of ANSI SQL/PSM
Home-page: https://github.com/mitakas/pygments-sql-pl-lexer
Author: Dimitar Dimitrov
Author-email: admin@mitakas.com
License: GPL
Keywords: pygments sql lexer
Platform: UNKNOWN
Requires-Dist: pygments (>=1.4)
